python_fortune_cookie/FortuneCookie.py
python_fortune_cookie/__init__.py
python_fortune_cookie/__main__.py
python_fortune_cookie-0.1.1.dist-info/LICENSE
python_fortune_cookie-0.1.1.dist-info/METADATA
python_fortune_cookie-0.1.1.dist-info/WHEEL
python_fortune_cookie-0.1.1.dist-info/entry_points.txt
python_fortune_cookie-0.1.1.dist-info/top_level.txt
python_fortune_cookie-0.1.1.dist-info/RECORD
