Metadata-Version: 2.1
Name: python_fortune_cookie
Version: 0.1.1
Summary: Fortune Cookie Generator for python.
Author-email: Yeshni Savadatti <ys4823@nyu.edu>, Lucia Song <lys7942@nyu.edu>, Chelsea Hodgson <csh7916@nyu.edu>, Alan Zhao <sz3562@nyu.edu>
License: GNU GENERAL PUBLIC LICENSE
Project-URL: Homepage, https://github.com/software-students-fall2024/3-python-package-scooby-gang
Project-URL: Repository, https://github.com/software-students-fall2024/3-python-package-scooby-gang.git
Project-URL: Bug Tracker, https://github.com/software-students-fall2024/3-python-package-scooby-gang/issues
Keywords: python,package,build,tutorial
Classifier: Programming Language :: Python :: 3
Classifier: Intended Audience :: Education
Classifier: License :: OSI Approved :: GNU General Public License v3 (GPLv3)
Classifier: Operating System :: OS Independent
Requires-Python: >=3.7
License-File: LICENSE
Requires-Dist: feedparser>=5.2.0
Requires-Dist: html2text
Requires-Dist: tomli; python_version < "3.11"
Provides-Extra: dev
Requires-Dist: pytest; extra == "dev"
Requires-Dist: bumpver; extra == "dev"
